palettable/__init__.py
palettable/palette.py
palettable/utils.py
palettable/cartocolors/__init__.py
palettable/cartocolors/cartocolorspalette.py
palettable/cartocolors/colormaps.py
palettable/cartocolors/diverging.py
palettable/cartocolors/qualitative.py
palettable/cartocolors/sequential.py
palettable/cmocean/__init__.py
palettable/cmocean/cmoceanpalette.py
palettable/cmocean/colormaps.py
palettable/cmocean/diverging.py
palettable/cmocean/sequential.py
palettable/colorbrewer/__init__.py
palettable/colorbrewer/colorbrewer.py
palettable/colorbrewer/colorbrewer_all_schemes.py
palettable/colorbrewer/diverging.py
palettable/colorbrewer/qualitative.py
palettable/colorbrewer/sequential.py
palettable/colorbrewer/data/colorbrewer_all_schemes.csv
palettable/colorbrewer/data/colorbrewer_all_schemes.json
palettable/colorbrewer/data/colorbrewer_licence.txt
palettable/colorbrewer/data/colorbrewer_schemes_csv_to_json.py
palettable/cubehelix/__init__.py
palettable/cubehelix/cubehelix.py
palettable/lightbartlein/__init__.py
palettable/lightbartlein/colordata.py
palettable/lightbartlein/diverging.py
palettable/lightbartlein/lightbartlein.py
palettable/lightbartlein/sequential.py
palettable/matplotlib/__init__.py
palettable/matplotlib/colormaps.py
palettable/matplotlib/matplotlib.py
palettable/mycarta/__init__.py
palettable/mycarta/colordata.py
palettable/mycarta/mycarta.py
palettable/scientific/__init__.py
palettable/scientific/colordata.py
palettable/scientific/diverging.py
palettable/scientific/scientific.py
palettable/scientific/sequential.py
palettable/tableau/__init__.py
palettable/tableau/tableau.py
palettable/wesanderson/__init__.py
palettable/wesanderson/wesanderson.py
palettable-3.3.2.dist-info/METADATA
palettable-3.3.2.dist-info/WHEEL
palettable-3.3.2.dist-info/top_level.txt
palettable-3.3.2.dist-info/RECORD
